adze/LICENSE.md
adze/README.md
adze/__init__.py
adze/boundary.py
adze/moments.py
adze/shapes.py
adze/split.py
adze/test_results.txt
adze/transform.py
adze/util.py
adze/voxel.py
adze/test/__init__.py
adze/test/conftest.py
adze/test/test_benchmarks.py
adze/test/test_split.py
adze/test/test_voxel.py
adze/test/utils.py
adze-0.2.dist-info/METADATA
adze-0.2.dist-info/WHEEL
adze-0.2.dist-info/licenses/LICENSE.md
adze-0.2.dist-info/RECORD
