Metadata-Version: 2.3
Name: adze
Version: 0.2
Summary: Polyhedron clipping and antialiased voxelization
Author-email: Jan Petykiewicz <jan@mpxd.net>
License: GNU Affero General Public License
License-File: LICENSE.md
Keywords: 3D,boolean,clip,clipping,geometric,geometry,moment,polyhedron,schlegel,split,voxel,voxelize
Classifier: Development Status :: 4 - Beta
Classifier: Intended Audience :: Developers
Classifier: Intended Audience :: Science/Research
Classifier: License :: OSI Approved :: GNU Affero General Public License v3
Classifier: Operating System :: OS Independent
Classifier: Programming Language :: Python :: 3
Classifier: Topic :: Multimedia :: Graphics
Classifier: Topic :: Scientific/Engineering
Requires-Python: >=3.11
Requires-Dist: numpy>=1.26
Provides-Extra: stl
Requires-Dist: stl; extra == 'stl'
